vsfemasr/__init__.py
vsfemasr/__main__.py
vsfemasr/fema_utils.py
vsfemasr/femasr_arch.py
vsfemasr/interpolate.py
vsfemasr/network_swinir.py
vsfemasr/vgg_arch.py
vsfemasr/models/FeMaSR_SRX2_model_g.pth
vsfemasr/models/FeMaSR_SRX4_model_g.pth
vsfemasr-2.0.0.dist-info/METADATA
vsfemasr-2.0.0.dist-info/WHEEL
vsfemasr-2.0.0.dist-info/licenses/LICENSE
vsfemasr-2.0.0.dist-info/RECORD
