Metadata-Version: 2.3
Name: vsfemasr
Version: 2.0.0
Summary: FeMaSR function for VapourSynth
Project-URL: Homepage, https://github.com/HolyWu/vs-femasr
Project-URL: Issues, https://github.com/HolyWu/vs-femasr/issues
Author-email: HolyWu <holywu@gmail.com>
License-File: LICENSE
Keywords: FeMaSR,PyTorch,TensorRT,VapourSynth
Classifier: Environment :: GPU :: NVIDIA CUDA
Classifier: License :: CC0 1.0 Universal (CC0 1.0) Public Domain Dedication
Classifier: Operating System :: OS Independent
Classifier: Programming Language :: Python :: 3
Classifier: Topic :: Multimedia :: Video
Requires-Python: >=3.10
Requires-Dist: numpy
Requires-Dist: requests
Requires-Dist: timm
Requires-Dist: torch>=2.4.0.dev
Requires-Dist: tqdm
Requires-Dist: vapoursynth>=66
